bot-resources/__init__.py
bot_resources/__init__.py
bot_resources/test.py
bot_resources/api/__init__.py
bot_resources/cmds/__init__.py
bot_resources/cmds/command.py
aidcraftbr-0.0.12.6.dist-info/LICENSE
aidcraftbr-0.0.12.6.dist-info/METADATA
aidcraftbr-0.0.12.6.dist-info/WHEEL
aidcraftbr-0.0.12.6.dist-info/top_level.txt
aidcraftbr-0.0.12.6.dist-info/RECORD
